README.md
setup.py
ibcli/cli.py
ibcli/configuration.py
ibcli/downloader.py
interactive_brokers_cli.egg-info/PKG-INFO
interactive_brokers_cli.egg-info/SOURCES.txt
interactive_brokers_cli.egg-info/dependency_links.txt
interactive_brokers_cli.egg-info/entry_points.txt
interactive_brokers_cli.egg-info/requires.txt
interactive_brokers_cli.egg-info/top_level.txt